slurmio/__init__.py
slurmio/slurmio.py
slurmio-0.1.2.dist-info/LICENSE
slurmio-0.1.2.dist-info/METADATA
slurmio-0.1.2.dist-info/WHEEL
slurmio-0.1.2.dist-info/top_level.txt
slurmio-0.1.2.dist-info/RECORD
