Metadata-Version: 2.2
Name: slurmio
Version: 0.1.2
Summary: Python tools to read SLURM job parameters
Author-email: Adam Tyson <code@adamltyson.com>
License: MIT
Project-URL: Homepage, https://github.com/neuroinformatics-unit/slurmio
Project-URL: Bug Tracker, https://github.com/neuroinformatics-unit/slurmio/issues
Project-URL: Documentation, https://github.com/neuroinformatics-unit/slurmio
Project-URL: Source Code, https://github.com/neuroinformatics-unit/slurmio
Project-URL: User Support, https://neuroinformatics.zulipchat.com/#narrow/stream/416291-slurmio
Classifier: Development Status :: 2 - Pre-Alpha
Classifier: Programming Language :: Python
Classifier: Programming Language :: Python :: 3
Classifier: Programming Language :: Python :: 3.11
Classifier: Programming Language :: Python :: 3.12
Classifier: Programming Language :: Python :: 3.13
Classifier: Operating System :: OS Independent
Classifier: License :: OSI Approved :: MIT License
Requires-Python: >=3.11
License-File: LICENSE
Provides-Extra: dev
Requires-Dist: pytest; extra == "dev"
Requires-Dist: pytest-cov; extra == "dev"
Requires-Dist: coverage; extra == "dev"
Requires-Dist: tox; extra == "dev"
Requires-Dist: black; extra == "dev"
Requires-Dist: mypy; extra == "dev"
Requires-Dist: pre-commit; extra == "dev"
Requires-Dist: ruff; extra == "dev"
Requires-Dist: setuptools_scm; extra == "dev"
